axmp_ai_conversation_completor/__init__.py
axmp_ai_conversation_completor/completion/sse_response_generator.py
axmp_ai_conversation_completor/scheme/chat_messages.py
axmp_ai_conversation_completor/util/graph_stream_utils.py
axmp_ai_conversation_completor-0.1.9.dist-info/LICENSE
axmp_ai_conversation_completor-0.1.9.dist-info/METADATA
axmp_ai_conversation_completor-0.1.9.dist-info/WHEEL
axmp_ai_conversation_completor-0.1.9.dist-info/RECORD
